{
    "checks": [
        {
            "id": "ConnectionStatus",
            "name": "Database connection Check",
            "description": "Checks that the database system is up and running by opening a connection.",
            "url": null,
            "parentId": null
        },
        {
            "id": "DomainExistsStatus",
            "name": "Domain Presence Check",
            "description": "Checks that at least one user domain is created in OBM.",
            "url": "http://obm.org/wiki/getting-started",
            "parentId": null
        },
        {
            "id": "DatabaseIntegrityStatus",
            "name": "Database Integrity Check",
            "description": "Checks the integrity of the OBM database.",
            "url": null,
            "parentId": null
        }
    ]
}
